shimmy/__init__.py
shimmy/bsuite_compatibility.py
shimmy/dm_control_compatibility.py
shimmy/dm_control_multiagent_compatibility.py
shimmy/dm_lab_compatibility.py
shimmy/meltingpot_compatibility.py
shimmy/openai_gym_compatibility.py
shimmy/openspiel_compatibility.py
shimmy/registration.py
shimmy/utils/__init__.py
shimmy/utils/dm_control_multiagent.py
shimmy/utils/dm_env.py
shimmy/utils/dm_lab.py
shimmy/utils/envs_configs.py
shimmy/utils/meltingpot.py
Shimmy-2.0.0.dist-info/METADATA
Shimmy-2.0.0.dist-info/WHEEL
Shimmy-2.0.0.dist-info/top_level.txt
Shimmy-2.0.0.dist-info/RECORD
