Metadata-Version: 2.1
Name: Shimmy
Version: 2.0.0
Summary: An API conversion tool providing Gymnasium and PettingZoo bindings for popular external reinforcement learning environments.
Home-page: https://github.com/Farama-Foundation/Shimmy
Author: Farama Foundation
Author-email: contact@farama.org
Keywords: Reinforcement Learning,game,RL,AI
Classifier: Programming Language :: Python :: 3.8
Classifier: Programming Language :: Python :: 3.9
Classifier: Programming Language :: Python :: 3.10
Classifier: Programming Language :: Python :: 3.11
Classifier: Programming Language :: Python :: 3.12
Classifier: License :: OSI Approved :: MIT License
Classifier: Operating System :: OS Independent
Requires-Python: >=3.8
Provides-Extra: gym-v21
Provides-Extra: gym-v26
Provides-Extra: dm-control
Provides-Extra: dm-control-multi-agent
Provides-Extra: dm-lab
Provides-Extra: openspiel
Provides-Extra: meltingpot
Provides-Extra: bsuite
Provides-Extra: all
Provides-Extra: testing
